{
  "kind": "collectionType",
  "collectionName": "practices",
  "info": {
    "singularName": "practice",
    "pluralName": "practices",
    "displayName": "Practice"
  },
  "options": {
    "draftAndPublish": false
  },
  "pluginOptions": {},
  "attributes": {
    "active": {
      "type": "boolean",
      "required": true,
      "default": false
    },
    "location": {
      "type": "relation",
      "relation": "oneToOne",
      "target": "api::location.location"
    },
    "start_time": {
      "type": "time",
      "required": true,
      "default": "18:00:00.000"
    },
    "end_time": {
      "type": "time"
    }
  }
}
